server_fastmcp.py
china_festival_mcp-0.1.12.dist-info/licenses/LICENSE
data/bazi_calculator.py
data/solar_terms.py
tools/__init__.py
tools/holiday.py
tools/weekday.py
utils/__init__.py
utils/date_utils.py
utils/logger.py
china_festival_mcp-0.1.12.dist-info/METADATA
china_festival_mcp-0.1.12.dist-info/WHEEL
china_festival_mcp-0.1.12.dist-info/entry_points.txt
china_festival_mcp-0.1.12.dist-info/top_level.txt
china_festival_mcp-0.1.12.dist-info/RECORD
