Metadata-Version: 2.4
Name: china-festival-mcp
Version: 0.1.12
Summary: 中国节假日和农历转换MCP服务器
Author-email: China Festival MCP <china-festival-mcp@example.com>
License: Apache-2.0
Project-URL: Homepage, https://github.com/your-username/china-festival-mcp
Project-URL: Repository, https://github.com/your-username/china-festival-mcp
Project-URL: Issues, https://github.com/your-username/china-festival-mcp/issues
Project-URL: Documentation, https://github.com/your-username/china-festival-mcp#readme
Keywords: mcp,china,festival,holiday,lunar,calendar,solar-terms
Classifier: Development Status :: 3 - Alpha
Classifier: Intended Audience :: Developers
Classifier: License :: OSI Approved :: Apache Software License
Classifier: Programming Language :: Python :: 3
Classifier: Programming Language :: Python :: 3.8
Classifier: Programming Language :: Python :: 3.9
Classifier: Programming Language :: Python :: 3.10
Classifier: Programming Language :: Python :: 3.11
Classifier: Programming Language :: Python :: 3.12
Classifier: Topic :: Software Development :: Libraries :: Python Modules
Classifier: Topic :: Utilities
Requires-Python: >=3.8
License-File: LICENSE
Requires-Dist: fastmcp>=0.1.0
Requires-Dist: httpx>=0.24.0
Requires-Dist: pydantic>=2.0.0
Provides-Extra: dev
Requires-Dist: pytest>=7.0.0; extra == "dev"
Requires-Dist: pytest-asyncio>=0.21.0; extra == "dev"
Requires-Dist: black>=23.0.0; extra == "dev"
Requires-Dist: isort>=5.12.0; extra == "dev"
Requires-Dist: mypy>=1.0.0; extra == "dev"
Dynamic: license-file
